odoo/addons/l10n_fr_pos_cert_allow_change_qty/README.rst
odoo/addons/l10n_fr_pos_cert_allow_change_qty/__init__.py
odoo/addons/l10n_fr_pos_cert_allow_change_qty/__manifest__.py
odoo/addons/l10n_fr_pos_cert_allow_change_qty/i18n/fr.po
odoo/addons/l10n_fr_pos_cert_allow_change_qty/i18n/l10n_fr_pos_cert_allow_change_qty.pot
odoo/addons/l10n_fr_pos_cert_allow_change_qty/readme/CONTRIBUTORS.rst
odoo/addons/l10n_fr_pos_cert_allow_change_qty/readme/DESCRIPTION.rst
odoo/addons/l10n_fr_pos_cert_allow_change_qty/readme/USAGE.rst
odoo/addons/l10n_fr_pos_cert_allow_change_qty/static/description/icon.png
odoo/addons/l10n_fr_pos_cert_allow_change_qty/static/description/index.html
odoo/addons/l10n_fr_pos_cert_allow_change_qty/static/src/js/pos.js
odoo/addons/l10n_fr_pos_cert_allow_change_qty/views/l10n_fr_pos_cert_allow_change_qty_templates.xml
odoo14_addon_l10n_fr_pos_cert_allow_change_qty-14.0.1.0.2.dev6.dist-info/METADATA
odoo14_addon_l10n_fr_pos_cert_allow_change_qty-14.0.1.0.2.dev6.dist-info/WHEEL
odoo14_addon_l10n_fr_pos_cert_allow_change_qty-14.0.1.0.2.dev6.dist-info/top_level.txt
odoo14_addon_l10n_fr_pos_cert_allow_change_qty-14.0.1.0.2.dev6.dist-info/RECORD
