Metadata-Version: 2.1
Name: odoo14-addon-l10n-fr-pos-cert-allow-change-qty
Version: 14.0.1.0.2.dev6
Summary: Remove restriction on change quantity
Home-page: https://github.com/OCA/l10n-france
Author: Le Filament, Odoo Community Association (OCA)
Author-email: support@odoo-community.org
License: AGPL-3
Platform: UNKNOWN
Classifier: Programming Language :: Python
Classifier: Framework :: Odoo
Classifier: Framework :: Odoo :: 14.0
Classifier: License :: OSI Approved :: GNU Affero General Public License v3
Requires-Python: >=3.6
Requires-Dist: odoo <14.1dev,>=14.0a
